2captcha_python_async-1.5.1.dist-info/licenses/LICENSE
twocaptcha/__init__.py
twocaptcha/api.py
twocaptcha/async_api.py
twocaptcha/async_solver.py
twocaptcha/solver.py
twocaptcha/exceptions/__init__.py
twocaptcha/exceptions/api.py
twocaptcha/exceptions/solver.py
2captcha_python_async-1.5.1.dist-info/METADATA
2captcha_python_async-1.5.1.dist-info/WHEEL
2captcha_python_async-1.5.1.dist-info/top_level.txt
2captcha_python_async-1.5.1.dist-info/RECORD
